rpa_toolkit/__init__.py
rpa_toolkit/excel.py
rpa_toolkit/pdf.py
rpa_toolkit/py.typed
rpa_toolkit-0.1.1.dist-info/licenses/LICENSE
rpa_toolkit-0.1.1.dist-info/WHEEL
rpa_toolkit-0.1.1.dist-info/METADATA
rpa_toolkit-0.1.1.dist-info/RECORD
