Metadata-Version: 2.4
Name: rpa-toolkit
Version: 0.1.1
Summary: A Python toolkit for Robotic Process Automation (RPA) with enhanced processing and solutions to common automation challenges.
Author: fnxL
Author-email: fnxL <48607132+fnxL@users.noreply.github.com>
License-Expression: MIT
License-File: LICENSE
Requires-Dist: fastexcel>=0.16.0
Requires-Dist: openpyxl>=3.1.5
Requires-Dist: polars>=1.34.0
Requires-Dist: pymupdf>=1.26.5
Requires-Dist: xlsx2csv>=0.8.4
Requires-Dist: xlsxwriter>=3.2.9
Requires-Python: >=3.10
Project-URL: Homepage, https://github.com/fnxL/rpa-toolkit
Project-URL: Issues, https://github.com/fnxL/rpa-toolkit/issues
